debug_print/__init__.py
debug_print2-0.1.2.dist-info/METADATA
debug_print2-0.1.2.dist-info/WHEEL
debug_print2-0.1.2.dist-info/RECORD
