Metadata-Version: 2.1
Name: debug-print2
Version: 0.1.2
Summary: Capture the print function and add some output information to it for easy debugging
Author: vvanglro
Requires-Python: >=3.8,<4.0
Classifier: Programming Language :: Python :: 3
Classifier: Programming Language :: Python :: 3.8
Classifier: Programming Language :: Python :: 3.9
Classifier: Programming Language :: Python :: 3.10
Classifier: Programming Language :: Python :: 3.11
